krippendorff_unitized_alpha/__init__.py
krippendorff_unitized_alpha/krippendorffs_unitized_alpha.py
krippendorff_unitized_alpha-0.1.0.dist-info/WHEEL
krippendorff_unitized_alpha-0.1.0.dist-info/METADATA
krippendorff_unitized_alpha-0.1.0.dist-info/RECORD
